a4f_local/__init__.py
a4f_local/client.py
a4f_local/providers/__init__.py
a4f_local/providers/_discovery.py
a4f_local/providers/provider_1/__init__.py
a4f_local/providers/provider_1/tts/__init__.py
a4f_local/providers/provider_1/tts/engine.py
a4f_local/types/__init__.py
a4f_local/types/audio.py
a4f_local/types/chat.py
a4f_local-0.1.1.dist-info/licenses/LICENSE
a4f_local-0.1.1.dist-info/METADATA
a4f_local-0.1.1.dist-info/WHEEL
a4f_local-0.1.1.dist-info/top_level.txt
a4f_local-0.1.1.dist-info/RECORD
