Metadata-Version: 2.4
Name: a4f-local
Version: 0.1.1
Summary: A unified wrapper for various reverse-engineered AI provider APIs, aiming for OpenAI compatibility.
Author: DevsDoCode
License: a4f-local - Software License Agreement
Project-URL: Homepage, https://github.com/Devs-Do-Code/a4f-local
Project-URL: Repository, https://github.com/Devs-Do-Code/a4f-local
Project-URL: YouTube, https://www.youtube.com/@DevsDoCode
Project-URL: Instagram, https://www.instagram.com/sree.shades_/
Project-URL: Twitter/X, https://x.com/Anand_Sreejan
Project-URL: Telegram, https://t.me/devsdocode
Project-URL: Discord, https://discord.com/invite/4gGcqsWWde
Project-URL: LinkedIn, https://www.linkedin.com/in/developer-sreejan/
Project-URL: Personal GitHub, https://github.com/SreejanPersonal
Keywords: openai,tts,ai,wrapper,reverse-engineering,api,text-to-speech
Classifier: Development Status :: 3 - Alpha
Classifier: Programming Language :: Python :: 3
Classifier: License :: Other/Proprietary License
Classifier: Operating System :: OS Independent
Classifier: Intended Audience :: Developers
Classifier: Topic :: Software Development :: Libraries :: Python Modules
Classifier: Topic :: Scientific/Engineering :: Artificial Intelligence
Requires-Python: >=3.8
License-File: LICENSE
Requires-Dist: requests>=2.20.0
Requires-Dist: pydantic>=2.0.0
Provides-Extra: test
Requires-Dist: pytest>=6.0; extra == "test"
Provides-Extra: docs
Requires-Dist: sphinx>=4.0.0; extra == "docs"
Requires-Dist: sphinx-rtd-theme>=1.0.0; extra == "docs"
Provides-Extra: dev
Requires-Dist: a4f-local[docs,test]; extra == "dev"
Requires-Dist: build; extra == "dev"
Requires-Dist: twine; extra == "dev"
Dynamic: license-file
